setup.py
django_sliver.egg-info/PKG-INFO
django_sliver.egg-info/SOURCES.txt
django_sliver.egg-info/dependency_links.txt
django_sliver.egg-info/not-zip-safe
django_sliver.egg-info/requires.txt
django_sliver.egg-info/top_level.txt
sliver/__init__.py
sliver/mixins.py
sliver/models.py
sliver/responses.py
sliver/tests.py
sliver/views.py