Metadata-Version: 1.0
Name: django-sliver
Version: 0.1.0
Summary: Lightweight REST API built on top of Django generic views
Home-page: https://github.com/jarcoal/django-sliver
Author: Jared Morse
Author-email: jarcoal@gmail.com
License: BSD
Keywords: django,api,rest
Platform: UNKNOWN
Classifier: Programming Language :: Python
Classifier: Topic :: Software Development :: Libraries :: Python Modules
Classifier: Framework :: Django
Classifier: Environment :: Web Environment
